pygwin/VERSION
pygwin/__init__.py
pygwin/_window_descriptors.py
pygwin/window.py
pygwin/window.pyi
pygame_window-1.0.0.dev2.dist-info/LICENSE.md
pygame_window-1.0.0.dev2.dist-info/METADATA
pygame_window-1.0.0.dev2.dist-info/WHEEL
pygame_window-1.0.0.dev2.dist-info/top_level.txt
pygame_window-1.0.0.dev2.dist-info/RECORD
