Metadata-Version: 2.1
Name: pygame-window
Version: 1.0.0.dev2
Summary: Enhanced window management and functionalities for Pygame
Home-page: https://pygame-window.readthedocs.io/en/latest/
Download-URL: https://pypi.org/project/pygame-window/
Author: Zenthm
Author-email: zenthm.dev@gmail.com
License: MIT
Project-URL: Bug Tracker, https://github.com/zenthm/pygame-window/issues
Project-URL: Documentation, https://pygame-window.readthedocs.io/en/latest/
Project-URL: Source Code, https://github.com/zenthm/pygame-window
Keywords: python,pygame,window,pygame-library,window-management,multiple-windows,pygame-window,pygame-sdl2
Classifier: Development Status :: 3 - Alpha
Classifier: Intended Audience :: Developers
Classifier: License :: OSI Approved :: MIT License
Classifier: Operating System :: Microsoft :: Windows
Classifier: Operating System :: POSIX
Classifier: Operating System :: Unix
Classifier: Operating System :: MacOS
Classifier: Programming Language :: Python
Classifier: Programming Language :: Python :: 3
Classifier: Programming Language :: Python :: 3 :: Only
Classifier: Programming Language :: Python :: 3.7
Classifier: Programming Language :: Python :: 3.8
Classifier: Programming Language :: Python :: 3.9
Classifier: Programming Language :: Python :: 3.10
Classifier: Topic :: Games/Entertainment
Classifier: Topic :: Software Development :: Libraries :: pygame
Requires-Python: >=3.7,<3.11
License-File: LICENSE.md
Requires-Dist: pygame (>=2.0.3)
Provides-Extra: all
Requires-Dist: black ; extra == 'all'
Provides-Extra: devs
Requires-Dist: black ; extra == 'devs'
Provides-Extra: docs
